sugar_mcp/__init__.py
sugar_mcp/__main__.py
sugar_mcp/cache.py
sugar_mcp/models.py
sugar_mcp/server.py
sugar_mcp-0.3.22.dist-info/LICENSE
sugar_mcp-0.3.22.dist-info/METADATA
sugar_mcp-0.3.22.dist-info/WHEEL
sugar_mcp-0.3.22.dist-info/entry_points.txt
sugar_mcp-0.3.22.dist-info/RECORD
