Metadata-Version: 2.3
Name: sugar-mcp
Version: 0.3.22
Summary: 
License: MIT
Author: yanrujing
Author-email: rujing.yan@protagonist-ai.com
Requires-Python: >=3.11,<4
Classifier: License :: OSI Approved :: MIT License
Classifier: Programming Language :: Python :: 3
Classifier: Programming Language :: Python :: 3.11
Classifier: Programming Language :: Python :: 3.12
Classifier: Programming Language :: Python :: 3.13
Requires-Dist: mcp (>=1.6.0,<2.0.0)
Requires-Dist: netmind-sugar (==0.3.7)
Requires-Dist: web3 (==7.12.0)
